<?xml version="1.0" encoding="UTF-8" standalone="no"?>
<event category="CREATE" id="0">
  <actions>
    <action id="603" library="1">
      <!--action name: Code-->
      <kind>CODE</kind>
      <allowRelative>false</allowRelative>
      <question>false</question>
      <canApplyTo>true</canApplyTo>
      <actionType>CODE</actionType>
      <functionName/>
      <relative>false</relative>
      <not>false</not>
      <appliesTo>.self</appliesTo>
      <arguments>
        <argument kind="STRING">isWalkable = true;
</argument>
      </arguments>
    </action>
    <action id="611" library="1">
      <!--action name: Variable-->
      <kind>VARIABLE</kind>
      <allowRelative>true</allowRelative>
      <question>false</question>
      <canApplyTo>true</canApplyTo>
      <actionType>CODE</actionType>
      <functionName/>
      <relative>false</relative>
      <not>false</not>
      <appliesTo>.self</appliesTo>
      <arguments>
        <argument kind="STRING">dirn</argument>
        <argument kind="EXPRESSION">0</argument>
      </arguments>
    </action>
    <action id="611" library="1">
      <!--action name: Variable-->
      <kind>VARIABLE</kind>
      <allowRelative>true</allowRelative>
      <question>false</question>
      <canApplyTo>true</canApplyTo>
      <actionType>CODE</actionType>
      <functionName/>
      <relative>false</relative>
      <not>false</not>
      <appliesTo>.self</appliesTo>
      <arguments>
        <argument kind="STRING">air</argument>
        <argument kind="EXPRESSION">0</argument>
      </arguments>
    </action>
    <action id="611" library="1">
      <!--action name: Variable-->
      <kind>VARIABLE</kind>
      <allowRelative>true</allowRelative>
      <question>false</question>
      <canApplyTo>true</canApplyTo>
      <actionType>CODE</actionType>
      <functionName/>
      <relative>false</relative>
      <not>false</not>
      <appliesTo>.self</appliesTo>
      <arguments>
        <argument kind="STRING">djump</argument>
        <argument kind="EXPRESSION">0</argument>
      </arguments>
    </action>
    <action id="611" library="1">
      <!--action name: Variable-->
      <kind>VARIABLE</kind>
      <allowRelative>true</allowRelative>
      <question>false</question>
      <canApplyTo>true</canApplyTo>
      <actionType>CODE</actionType>
      <functionName/>
      <relative>false</relative>
      <not>false</not>
      <appliesTo>.self</appliesTo>
      <arguments>
        <argument kind="STRING">dsmash</argument>
        <argument kind="EXPRESSION">0</argument>
      </arguments>
    </action>
    <action id="611" library="1">
      <!--action name: Variable-->
      <kind>VARIABLE</kind>
      <allowRelative>true</allowRelative>
      <question>false</question>
      <canApplyTo>true</canApplyTo>
      <actionType>CODE</actionType>
      <functionName/>
      <relative>false</relative>
      <not>false</not>
      <appliesTo>.self</appliesTo>
      <arguments>
        <argument kind="STRING">hurt</argument>
        <argument kind="EXPRESSION">0</argument>
      </arguments>
    </action>
    <action id="611" library="1">
      <!--action name: Variable-->
      <kind>VARIABLE</kind>
      <allowRelative>true</allowRelative>
      <question>false</question>
      <canApplyTo>true</canApplyTo>
      <actionType>CODE</actionType>
      <functionName/>
      <relative>false</relative>
      <not>false</not>
      <appliesTo>.self</appliesTo>
      <arguments>
        <argument kind="STRING">splapplespeed</argument>
        <argument kind="EXPRESSION">10</argument>
      </arguments>
    </action>
    <action id="611" library="1">
      <!--action name: Variable-->
      <kind>VARIABLE</kind>
      <allowRelative>true</allowRelative>
      <question>false</question>
      <canApplyTo>true</canApplyTo>
      <actionType>CODE</actionType>
      <functionName/>
      <relative>false</relative>
      <not>false</not>
      <appliesTo>.self</appliesTo>
      <arguments>
        <argument kind="STRING">spinjump</argument>
        <argument kind="EXPRESSION">0</argument>
      </arguments>
    </action>
    <action id="611" library="1">
      <!--action name: Variable-->
      <kind>VARIABLE</kind>
      <allowRelative>true</allowRelative>
      <question>false</question>
      <canApplyTo>true</canApplyTo>
      <actionType>CODE</actionType>
      <functionName/>
      <relative>false</relative>
      <not>false</not>
      <appliesTo>.self</appliesTo>
      <arguments>
        <argument kind="STRING">djumpable</argument>
        <argument kind="EXPRESSION">1</argument>
      </arguments>
    </action>
    <action id="611" library="1">
      <!--action name: Variable-->
      <kind>VARIABLE</kind>
      <allowRelative>true</allowRelative>
      <question>false</question>
      <canApplyTo>true</canApplyTo>
      <actionType>CODE</actionType>
      <functionName/>
      <relative>false</relative>
      <not>false</not>
      <appliesTo>.self</appliesTo>
      <arguments>
        <argument kind="STRING">newmsps</argument>
        <argument kind="EXPRESSION">0</argument>
      </arguments>
    </action>
    <action id="611" library="1">
      <!--action name: Variable-->
      <kind>VARIABLE</kind>
      <allowRelative>true</allowRelative>
      <question>false</question>
      <canApplyTo>true</canApplyTo>
      <actionType>CODE</actionType>
      <functionName/>
      <relative>false</relative>
      <not>false</not>
      <appliesTo>.self</appliesTo>
      <arguments>
        <argument kind="STRING">newmsao</argument>
        <argument kind="EXPRESSION">0</argument>
      </arguments>
    </action>
    <action id="611" library="1">
      <!--action name: Variable-->
      <kind>VARIABLE</kind>
      <allowRelative>true</allowRelative>
      <question>false</question>
      <canApplyTo>true</canApplyTo>
      <actionType>CODE</actionType>
      <functionName/>
      <relative>false</relative>
      <not>false</not>
      <appliesTo>.self</appliesTo>
      <arguments>
        <argument kind="STRING">newlives</argument>
        <argument kind="EXPRESSION">0</argument>
      </arguments>
    </action>
    <action id="611" library="1">
      <!--action name: Variable-->
      <kind>VARIABLE</kind>
      <allowRelative>true</allowRelative>
      <question>false</question>
      <canApplyTo>true</canApplyTo>
      <actionType>CODE</actionType>
      <functionName/>
      <relative>false</relative>
      <not>false</not>
      <appliesTo>.self</appliesTo>
      <arguments>
        <argument kind="STRING">tjumping</argument>
        <argument kind="EXPRESSION">0</argument>
      </arguments>
    </action>
    <action id="611" library="1">
      <!--action name: Variable-->
      <kind>VARIABLE</kind>
      <allowRelative>true</allowRelative>
      <question>false</question>
      <canApplyTo>true</canApplyTo>
      <actionType>CODE</actionType>
      <functionName/>
      <relative>false</relative>
      <not>false</not>
      <appliesTo>.self</appliesTo>
      <arguments>
        <argument kind="STRING">ssmashng</argument>
        <argument kind="EXPRESSION">0</argument>
      </arguments>
    </action>
    <action id="611" library="1">
      <!--action name: Variable-->
      <kind>VARIABLE</kind>
      <allowRelative>true</allowRelative>
      <question>false</question>
      <canApplyTo>true</canApplyTo>
      <actionType>CODE</actionType>
      <functionName/>
      <relative>false</relative>
      <not>false</not>
      <appliesTo>.self</appliesTo>
      <arguments>
        <argument kind="STRING">hovered</argument>
        <argument kind="EXPRESSION">0</argument>
      </arguments>
    </action>
    <action id="611" library="1">
      <!--action name: Variable-->
      <kind>VARIABLE</kind>
      <allowRelative>true</allowRelative>
      <question>false</question>
      <canApplyTo>true</canApplyTo>
      <actionType>CODE</actionType>
      <functionName/>
      <relative>false</relative>
      <not>false</not>
      <appliesTo>.self</appliesTo>
      <arguments>
        <argument kind="STRING">running</argument>
        <argument kind="EXPRESSION">0</argument>
      </arguments>
    </action>
    <action id="611" library="1">
      <!--action name: Variable-->
      <kind>VARIABLE</kind>
      <allowRelative>true</allowRelative>
      <question>false</question>
      <canApplyTo>true</canApplyTo>
      <actionType>CODE</actionType>
      <functionName/>
      <relative>false</relative>
      <not>false</not>
      <appliesTo>.self</appliesTo>
      <arguments>
        <argument kind="STRING">charging</argument>
        <argument kind="EXPRESSION">0</argument>
      </arguments>
    </action>
    <action id="611" library="1">
      <!--action name: Variable-->
      <kind>VARIABLE</kind>
      <allowRelative>true</allowRelative>
      <question>false</question>
      <canApplyTo>true</canApplyTo>
      <actionType>CODE</actionType>
      <functionName/>
      <relative>false</relative>
      <not>false</not>
      <appliesTo>.self</appliesTo>
      <arguments>
        <argument kind="STRING">runcharge</argument>
        <argument kind="EXPRESSION">0</argument>
      </arguments>
    </action>
    <action id="611" library="1">
      <!--action name: Variable-->
      <kind>VARIABLE</kind>
      <allowRelative>true</allowRelative>
      <question>false</question>
      <canApplyTo>true</canApplyTo>
      <actionType>CODE</actionType>
      <functionName/>
      <relative>false</relative>
      <not>false</not>
      <appliesTo>.self</appliesTo>
      <arguments>
        <argument kind="STRING">icedirn</argument>
        <argument kind="EXPRESSION">90</argument>
      </arguments>
    </action>
    <action id="611" library="1">
      <!--action name: Variable-->
      <kind>VARIABLE</kind>
      <allowRelative>true</allowRelative>
      <question>false</question>
      <canApplyTo>true</canApplyTo>
      <actionType>CODE</actionType>
      <functionName/>
      <relative>false</relative>
      <not>false</not>
      <appliesTo>.self</appliesTo>
      <arguments>
        <argument kind="STRING">icerun</argument>
        <argument kind="EXPRESSION">0</argument>
      </arguments>
    </action>
    <action id="611" library="1">
      <!--action name: Variable-->
      <kind>VARIABLE</kind>
      <allowRelative>true</allowRelative>
      <question>false</question>
      <canApplyTo>true</canApplyTo>
      <actionType>CODE</actionType>
      <functionName/>
      <relative>false</relative>
      <not>false</not>
      <appliesTo>.self</appliesTo>
      <arguments>
        <argument kind="STRING">icespeed</argument>
        <argument kind="EXPRESSION">4</argument>
      </arguments>
    </action>
    <action id="611" library="1">
      <!--action name: Variable-->
      <kind>VARIABLE</kind>
      <allowRelative>true</allowRelative>
      <question>false</question>
      <canApplyTo>true</canApplyTo>
      <actionType>CODE</actionType>
      <functionName/>
      <relative>false</relative>
      <not>false</not>
      <appliesTo>.self</appliesTo>
      <arguments>
        <argument kind="STRING">pootis</argument>
        <argument kind="EXPRESSION">0</argument>
      </arguments>
    </action>
    <action id="611" library="1">
      <!--action name: Variable-->
      <kind>VARIABLE</kind>
      <allowRelative>true</allowRelative>
      <question>false</question>
      <canApplyTo>true</canApplyTo>
      <actionType>CODE</actionType>
      <functionName/>
      <relative>false</relative>
      <not>false</not>
      <appliesTo>.self</appliesTo>
      <arguments>
        <argument kind="STRING">gottam</argument>
        <argument kind="EXPRESSION">0</argument>
      </arguments>
    </action>
    <action id="611" library="1">
      <!--action name: Variable-->
      <kind>VARIABLE</kind>
      <allowRelative>true</allowRelative>
      <question>false</question>
      <canApplyTo>true</canApplyTo>
      <actionType>CODE</actionType>
      <functionName/>
      <relative>false</relative>
      <not>false</not>
      <appliesTo>.self</appliesTo>
      <arguments>
        <argument kind="STRING">dsmashed</argument>
        <argument kind="EXPRESSION">0</argument>
      </arguments>
    </action>
    <action id="541" library="1">
      <!--action name: Set_Sprite-->
      <kind>NORMAL</kind>
      <allowRelative>false</allowRelative>
      <question>false</question>
      <canApplyTo>true</canApplyTo>
      <actionType>FUNCTION</actionType>
      <functionName>action_sprite_set</functionName>
      <relative>false</relative>
      <not>false</not>
      <appliesTo>.self</appliesTo>
      <arguments>
        <argument kind="SPRITE">RedApple</argument>
        <argument kind="EXPRESSION">0</argument>
        <argument kind="EXPRESSION">0</argument>
      </arguments>
    </action>
    <action id="603" library="1">
      <!--action name: Code-->
      <kind>CODE</kind>
      <allowRelative>false</allowRelative>
      <question>false</question>
      <canApplyTo>true</canApplyTo>
      <actionType>CODE</actionType>
      <functionName/>
      <relative>false</relative>
      <not>false</not>
      <appliesTo>.self</appliesTo>
      <arguments>
        <argument kind="STRING">rapiddsmash=false;
usmashing=false;
groundspeed=4;
if global.cheat_SUPER_SPEED=true groundspeed*=4;
beerdirection = -1;
beerdirectionlast = -1;
pinkrofljumps = 0;
wasdsmashingatthestartofthisstep = dsmash;

var CUM;
CUM = "pinkparticlesystem = part_system_create();
pinkparticletype = part_type_create();
part_type_sprite(pinkparticletype,spr_PinkRoflcopter,true,false,true);
part_type_direction(pinkparticletype,0,359,1,0);
part_type_speed(pinkparticletype,2,5,-0.1,0);
part_type_alpha2(pinkparticletype,0.5,0);
part_type_blend(pinkparticletype,false);
part_type_scale(pinkparticletype,0.5,0.5);
part_type_life(pinkparticletype, 30, 60);
part_type_gravity(pinkparticletype,0.3,90);
part_system_depth(pinkparticlesystem,11);";

wallslide = "none";
wallforce = "none";

slimeparticlesystem = part_system_create();
slimeparticletype = part_type_create();
part_type_sprite(slimeparticletype,StickyParticle,true,false,true);
part_type_size(slimeparticletype,0.2,0.7,-0.01,0.1);
part_type_life(slimeparticletype, 15, 45);
part_type_gravity(slimeparticletype,0.4,270);
part_type_orientation(slimeparticletype,0,359,0,3,false);
part_system_depth(slimeparticlesystem,-10);

yellowstarfieldparticlesystem = part_system_create();
yellowstarfieldparticletype = part_type_create();
part_type_sprite(yellowstarfieldparticletype,Star,true,true,false);
part_type_size(yellowstarfieldparticletype,0.05,0.15,0,0);
part_type_life(yellowstarfieldparticletype, 5, 15);
part_type_orientation(yellowstarfieldparticletype,0,359,5,0,false);
part_system_depth(yellowstarfieldparticlesystem,9);

slimebuildup = 0;

controller_maxtilt = 0.7
controller_speedmultiplier = 1
controller_deadzone = 0.1

global.timer = 0
</argument>
      </arguments>
    </action>
    <action id="603" library="1">
      <!--action name: Code-->
      <kind>CODE</kind>
      <allowRelative>false</allowRelative>
      <question>false</question>
      <canApplyTo>true</canApplyTo>
      <actionType>CODE</actionType>
      <functionName/>
      <relative>false</relative>
      <not>false</not>
      <appliesTo>.self</appliesTo>
      <arguments>
        <argument kind="STRING">movementTimer = 0;
</argument>
      </arguments>
    </action>
  </actions>
</event>
